[{"model": "auth.user", "pk": 1, "fields": {"password": "pbkdf2_sha256$1200000$jHZKgamDU3d7KqKhDRpf06$VJ4z2Ov8LCQfq1nJSvRzVWtXJqw1pvSIO8WgGIZPvPY=", "last_login": "2026-01-15T04:52:29.128Z", "is_superuser": true, "username": "admin", "first_name": "", "last_name": "", "email": "", "is_staff": true, "is_active": true, "date_joined": "2026-01-14T05:21:45.238Z", "groups": [], "user_permissions": []}}, {"model": "auth.user", "pk": 2, "fields": {"password": "pbkdf2_sha256$1200000$Ecz0HAftrdyMZfmS6szCKt$C5CKvBNzB2ji6iUjYKjqfNO8oJFciyCOurwRqBxhYNM=", "last_login": null, "is_superuser": false, "username": "sabin", "first_name": "", "last_name": "", "email": "sabin@gmail.com", "is_staff": false, "is_active": true, "date_joined": "2026-01-16T04:56:51.800Z", "groups": [], "user_permissions": []}}, {"model": "employees.lead", "pk": 4, "fields": {"user": 2, "lead_name": "Jithinn", "email": "jithin@gmail.com", "phone": "5243435353", "created_at": "2026-01-16T05:36:03.746Z"}}, {"model": "employees.works", "pk": 1, "fields": {"user": null, "work_name": "WebSite Design", "description": "Design attractive ui for home page", "lead": null, "created_at": "2026-01-15T09:42:29.142Z"}}, {"model": "employees.works", "pk": 2, "fields": {"user": 2, "work_name": "WebsiteDesign", "description": "Design a home ui", "lead": 4, "created_at": "2026-01-16T05:42:55.618Z"}}, {"model": "employees.works", "pk": 6, "fields": {"user": 2, "work_name": "test", "description": "test", "lead": 4, "created_at": "2026-01-18T13:51:13.901Z"}}, {"model": "employees.employee", "pk": 2, "fields": {"user": null, "emp_name": "Anandhu", "emp_mob": "9292929292", "emp_salary": 25000, "department": "Python", "lead": null, "profile_photo": "employee_photos/anandhu.jpg", "is_active": false, "created_at": "2026-01-15T09:36:44.286Z"}}, {"model": "employees.employee", "pk": 3, "fields": {"user": null, "emp_name": "midhun", "emp_mob": "1234567890", "emp_salary": 23333, "department": "NetWorking", "lead": null, "profile_photo": "", "is_active": false, "created_at": "2026-01-15T09:37:38.710Z"}}, {"model": "employees.employee", "pk": 4, "fields": {"user": null, "emp_name": "Jhon", "emp_mob": "6756745678", "emp_salary": 25666, "department": "Mern", "lead": null, "profile_photo": "", "is_active": false, "created_at": "2026-01-15T10:07:30.152Z"}}, {"model": "employees.employee", "pk": 5, "fields": {"user": 2, "emp_name": "Yadhul", "emp_mob": "6738383834", "emp_salary": 24336, "department": "Python", "lead": 4, "profile_photo": "employee_photos/yadhul.jpg", "is_active": false, "created_at": "2026-01-16T05:17:44.823Z"}}, {"model": "employees.assignedwork", "pk": 1, "fields": {"employee": 5, "work": 2, "assigned_date": "2026-01-18T13:11:18.099Z", "is_completed": true}}, {"model": "employees.assignedwork", "pk": 4, "fields": {"employee": 5, "work": 6, "assigned_date": "2026-01-18T13:51:20.198Z", "is_completed": true}}]
